Metadata-Version: 2.1
Name: simplelayout-aoweiie
Version: 1.0.0
Summary: a simple layout generator project
Home-page: https://github.com/idrl-assignment/3-simplelayout-package-aoweiie
Author: Yao WJ
Author-email: 996267113@qq.com
License: UNKNOWN
Project-URL: Source, https://github.com/idrl-assignment/3-simplelayout-package-aoweiie
Keywords: layout
Platform: UNKNOWN
Classifier: Development Status :: 3 - Alpha
Classifier: License :: OSI Approved :: MIT License
Classifier: Programming Language :: Python :: 3
Requires-Dist: numpy
Requires-Dist: matplotlib
Requires-Dist: scipy
